{
  "id": "ysad-042",
  "title": "YSAD-042 When I pacopaco with my uncle, Omata jinjin. - Mihina (Azumi Hina, Nagai Mihina)",
  "description": "A middle-aged uncle who forcibly kisses with a fishy mouth and entangles his tongue. A lot of metamorphosis that licks chestnuts, ma ● ko and anal with a rough tongue covered with saliva and licks again with its mouth. If you put the whole weight on a thick meat stick and insert it into a tight-fitting girl, the girl's discomfort turns into pleasure and she shakes her hips and asks for a fierce thrust. The women whose mouths and mako are covered with semen by a middle-aged man who has an aging smell still continue to live.",
  "poster": "https://fourhoi.com/ysad-042/cover-n.jpg",
  "release_date": "2020-08-28",
  "duration": 8477,
  "genres": [
    "Cunnilingus",
    "Creampie",
    "Forced Blowjob",
    "Collection",
    "Hd"
  ],
  "cast": [
    "Mihina (Azumi Hina, Nagai Mihina)",
    "Pure White Here",
    "Mai Imai",
    "Hinami Yumesaki",
    "Kotone Fuyue",
    "Mizuki Yayoi",
    "Tsugumi Mizusawa"
  ],
  "maker": "光夜蝶",
  "sources": [
    {
      "name": "High Quality",
      "url": "https://hls.lustyflix.com/proxy?url=",
      "type": "hls"
    },
    {
      "name": "Medium Quality",
      "url": "https://hls.lustyflix.com/proxy?url=",
      "type": "hls"
    },
    {
      "name": "Low Quality",
      "url": "https://hls.lustyflix.com/proxy?url=",
      "type": "hls"
    }
  ],
  "url": "https://missav.ws/dm13/en/ysad-042"
}