{
  "id": "abba-484",
  "title": "ABBA-484 An Aunt Teacher Who Was Defeated By A Student Who Was Despised Because It Was A Virgin",
  "description": "\"I'd like you to teach me health and physical education in detail ... Oh, I'm feeling sick, right?\" In the classroom, you can have a mischievous 3P in the health room as much as you want! !! Don't touch anything weird because it's in class ... Check the wetness of a beautiful teacher whose beautiful legs are dazzling from a tight skirt, and take care of a slender fifty aunt teacher regardless of where the problem child is! !! A Married Woman Teacher With Big Tits Forty Who Feels With A Brush Wholesale That A Virgin Cock Relentlessly Goes Into The Uterus ... 8 Hours Of Frenzy Creampie Of 30 Mature Teachers Who Completely Fallen Into A Student's Robust Meat Stick! !!",
  "poster": "https://fourhoi.com/abba-484/cover-n.jpg",
  "release_date": "2020-08-20",
  "duration": 7773,
  "genres": [
    "Mature Woman",
    "Female Teacher",
    "Virgin",
    "Creampie",
    "Collection",
    "4 Hours Or More",
    "Hd"
  ],
  "cast": [],
  "maker": "センタービレッジ",
  "sources": [
    {
      "name": "High Quality",
      "url": "https://hls.lustyflix.com/proxy?url=",
      "type": "hls"
    },
    {
      "name": "Medium Quality",
      "url": "https://hls.lustyflix.com/proxy?url=",
      "type": "hls"
    },
    {
      "name": "Low Quality",
      "url": "https://hls.lustyflix.com/proxy?url=",
      "type": "hls"
    }
  ],
  "url": "https://missav.ws/dm19/en/abba-484"
}