{
  "id": "pts-470",
  "title": "PTS-470 Married Woman Luxury Oil Esthetic Restraint Lesbian! 8 hours omnibus - Nao Mizushiro",
  "description": null,
  "poster": "https://fourhoi.com/pts-470/cover-n.jpg",
  "release_date": "2020-09-15",
  "duration": 7216,
  "genres": [
    "Restraint",
    "Wife",
    "Lesbian",
    "Lesbian Kiss",
    "Collection",
    "4 Hours Or More",
    "Hd"
  ],
  "cast": [
    "Nao Mizushiro",
    "Hibiki Otsuki",
    "Hamazaki Mao",
    "Mary Tachibana",
    "Kanna Misaki",
    "Yurina Aizawa",
    "Miyuki Sakura",
    "Yuna Ishikawa",
    "Takarada Monami",
    "Im Sorry"
  ],
  "maker": "ピーターズ",
  "sources": [
    {
      "name": "High Quality",
      "url": "https://hls.lustyflix.com/proxy?url=",
      "type": "hls"
    },
    {
      "name": "Medium Quality",
      "url": "https://hls.lustyflix.com/proxy?url=",
      "type": "hls"
    },
    {
      "name": "Low Quality",
      "url": "https://hls.lustyflix.com/proxy?url=",
      "type": "hls"
    }
  ],
  "url": "https://missav.ws/dm19/en/pts-470"
}