{
  "id": "t28-593",
  "title": "T28-593 play video of a devil father who keeps committing his beloved daughter Erina Oka - Erina Hill",
  "description": "\"Dad, this is the end ...\" A devil father who loves his daughter and continues to devour him absurdly. The desire for control that becomes stronger day by day, the youth of the daughter is twisted and forcibly made into my own. The struggle of a daughter who feels suspicion about her father and pleasure in her indecentness that accompanies her adolescence. A sigh that leaks even if you put up with it and kill it, a nasty body that reacts every time you touch it. Accelerating eccentricity, falling into a whirlpool of endless pleasures ...",
  "poster": "https://fourhoi.com/t28-593/cover-n.jpg",
  "release_date": "2020-08-28",
  "duration": 8138,
  "genres": [
    "Cruel",
    "Incest",
    "Individual",
    "Hd"
  ],
  "cast": [
    "Erina Hill"
  ],
  "maker": "TMA",
  "sources": [
    {
      "name": "High Quality",
      "url": "https://hls.lustyflix.com/proxy?url=",
      "type": "hls"
    },
    {
      "name": "Medium Quality",
      "url": "https://hls.lustyflix.com/proxy?url=",
      "type": "hls"
    },
    {
      "name": "Low Quality",
      "url": "https://hls.lustyflix.com/proxy?url=",
      "type": "hls"
    }
  ],
  "url": "https://missav.ws/dm13/en/t28-593"
}