{
  "id": "fsdss-093",
  "title": "FSDSS-093 Her First Orgasmic Shameful Massive Flooding And Squirting Experience SPECIAL Natsu Tojo",
  "description": "Beautiful girl slender Natsu Tojo was too embarrassed to be NG \"Peeing\" ban first challenge! Nacchan, who had declared that she wouldn't go out except in the bathroom, urinates in front of the camera! !! Extreme shame on unstoppable pee! Did the limiter come off due to the successful leak and became incontinence? A big flood that can not be stopped with a piston at 69 with a blowjob!",
  "poster": "https://fourhoi.com/fsdss-093/cover-n.jpg",
  "release_date": "2020-09-10",
  "duration": 7408,
  "genres": [
    "Pretty Girl",
    "Slim",
    "Individual",
    "Urinate",
    "Squirting",
    "Hd"
  ],
  "cast": [
    "Natsu Tojo"
  ],
  "maker": "FALENO",
  "sources": [
    {
      "name": "High Quality",
      "url": "https://hls.lustyflix.com/proxy?url=",
      "type": "hls"
    },
    {
      "name": "Medium Quality",
      "url": "https://hls.lustyflix.com/proxy?url=",
      "type": "hls"
    },
    {
      "name": "Low Quality",
      "url": "https://hls.lustyflix.com/proxy?url=",
      "type": "hls"
    }
  ],
  "url": "https://missav.ws/dm18/en/fsdss-093"
}