{"ylwn-132":"en/yl/wn/-1/en-ylwn-132.json","ylwn-133":"en/yl/wn/-1/en-ylwn-133.json","ykmc-034":"en/yk/mc/-0/en-ykmc-034.json","ymdd-206":"en/ym/dd/-2/en-ymdd-206.json","ymdd-204":"en/ym/dd/-2/en-ymdd-204.json","ymdd-203":"en/ym/dd/-2/en-ymdd-203.json","ymdd-205":"en/ym/dd/-2/en-ymdd-205.json","yst-227":"en/ys/t-/22/en-yst-227.json","ysn-522":"en/ys/n-/52/en-ysn-522.json","yst-226":"en/ys/t-/22/en-yst-226.json","ysn-523":"en/ys/n-/52/en-ysn-523.json","ytr-146":"en/yt/r-/14/en-ytr-146.json","ysn-521":"en/ys/n-/52/en-ysn-521.json","ysad-042":"en/ys/ad/-0/en-ysad-042.json","yako-015":"en/ya/ko/-0/en-yako-015.json","yami-096":"en/ya/mi/-0/en-yami-096.json","ykmc-033":"en/yk/mc/-0/en-ykmc-033.json","yoz-380":"en/yo/z-/38/en-yoz-380.json","yros-001":"en/yr/os/-0/en-yros-001.json"}