{
  "id": "nsstl-034",
  "title": "NSSTL-034 Affair Wife Iroha Narimiya Iroha Immoral Sex In The Afternoon",
  "description": "A wife who treats her husband as a housemate. I have had a physical relationship with a courier for about half a year. Although the relationship with her husband was broken, she became intimate with the courier who would eliminate her libido.",
  "poster": "https://fourhoi.com/nsstl-034/cover-n.jpg",
  "release_date": "2020-09-01",
  "duration": 2359,
  "genres": [
    "Wife",
    "Adultery",
    "Individual",
    "Ntr",
    "Plot",
    "Hd",
    "Exclusive"
  ],
  "cast": [
    "Narimiya Iroha"
  ],
  "maker": "ながえスタイル",
  "sources": [
    {
      "name": "High Quality",
      "url": "https://hls.lustyflix.com/proxy?url=",
      "type": "hls"
    },
    {
      "name": "Medium Quality",
      "url": "https://hls.lustyflix.com/proxy?url=",
      "type": "hls"
    },
    {
      "name": "Low Quality",
      "url": "https://hls.lustyflix.com/proxy?url=",
      "type": "hls"
    }
  ],
  "url": "https://missav.ws/dm21/en/nsstl-034"
}