{
  "id": "mkmp-348",
  "title": "MKMP-348 Double H-Cup Titties Jiggling And Wiggling Big Tits Stuffed Into A Micro Bikini Mid-Summer Poolside Sex Ruka Inaba Tsugumi Morimoto",
  "description": "Ruka Inaba & Tsugumi Morimoto. Double H cup big breasts have poolside sex in a racy micro bikini! !! Two people who are not spoiled in the pool in the middle of summer seduce men one after another! ?? Close contact H cup boobs pressing & Prun Prun disturbed 3P sex '1 vs 1 sex'. The finish is all 5 thick ejaculations on naughty boobs! !!",
  "poster": "https://fourhoi.com/mkmp-348/cover-n.jpg",
  "release_date": "2020-08-14",
  "duration": 9540,
  "genres": [
    "Big Breasts",
    "Swimsuit",
    "Ride",
    "Orgy",
    "Subjective Perspective",
    "Hd"
  ],
  "cast": [
    "Ruka Inaba",
    "Tsugumi Morimoto"
  ],
  "maker": "KM Produce",
  "sources": [
    {
      "name": "High Quality",
      "url": "https://hls.lustyflix.com/proxy?url=",
      "type": "hls"
    },
    {
      "name": "Medium Quality",
      "url": "https://hls.lustyflix.com/proxy?url=",
      "type": "hls"
    },
    {
      "name": "Low Quality",
      "url": "https://hls.lustyflix.com/proxy?url=",
      "type": "hls"
    }
  ],
  "url": "https://missav.ws/dm24/en/mkmp-348"
}