{
  "id": "dpsdl-007",
  "title": "DPSDL-007 A genius of full-body kissing that licks from the top of the head to the soles of the feet covered with spills. East ○ Outside ○○ University 4th year Haruka Takami Haruka",
  "description": "Nostril drill licking, head licking, ear licking, armpit licking, licking the navel hole with the tongue, sucking toes, licking from the anus to the gold ball! Haruka-chan licks the whole body of a man who himself made a shaved head with a hair clipper with his tongue and tastes it T ○ EIC 880 points exceeded Highly educated JD whole body licking SEX!",
  "poster": "https://fourhoi.com/dpsdl-007/cover-n.jpg",
  "release_date": "2020-08-19",
  "duration": 7207,
  "genres": [
    "Female College Student",
    "Pretty Girl",
    "Individual",
    "Kiss",
    "Oral Sex",
    "Hd",
    "Exclusive"
  ],
  "cast": [
    "Haruka Takami"
  ],
  "maker": "DEEP'S",
  "sources": [
    {
      "name": "High Quality",
      "url": "https://hls.lustyflix.com/proxy?url=",
      "type": "hls"
    },
    {
      "name": "Medium Quality",
      "url": "https://hls.lustyflix.com/proxy?url=",
      "type": "hls"
    },
    {
      "name": "Low Quality",
      "url": "https://hls.lustyflix.com/proxy?url=",
      "type": "hls"
    }
  ],
  "url": "https://missav.ws/dm19/en/dpsdl-007"
}