{
  "id": "anx-127",
  "title": "ANX-127 First event ● Addiction Her first menarche -First- Sara Kagami - Kagami Sara",
  "description": "She fell in love at first sight at the audition. Event ● The condition of the test was very good. Immediately negotiate for shooting, no, after that ... Negotiations concluded → Immediately held ● Enjoy the real thrill of it. It's the first time, but it's amazing, really. If you are in a stunned state at any time (self-finger or camera gaze), then any suggestion will pass! I performed as much as I could think of with ad lib. Such a beautiful girl ... Enjoy her first experience! !!",
  "poster": "https://fourhoi.com/anx-127/cover-n.jpg",
  "release_date": "2020-09-13",
  "duration": 6821,
  "genres": [
    "Pretty Girl",
    "Documentary",
    "Individual",
    "Hd",
    "Exclusive",
    "Delusion"
  ],
  "cast": [
    "Kagami Sara"
  ],
  "maker": "ヒプノシスラボ/妄想族",
  "sources": [
    {
      "name": "High Quality",
      "url": "https://hls.lustyflix.com/proxy?url=",
      "type": "hls"
    },
    {
      "name": "Medium Quality",
      "url": "https://hls.lustyflix.com/proxy?url=",
      "type": "hls"
    },
    {
      "name": "Low Quality",
      "url": "https://hls.lustyflix.com/proxy?url=",
      "type": "hls"
    }
  ],
  "url": "https://missav.ws/dm19/en/anx-127"
}