{
  "id": "orec-582",
  "title": "OREC-582 Echika",
  "description": null,
  "poster": "https://fourhoi.com/orec-582/cover-n.jpg",
  "release_date": "2020-09-14",
  "duration": 3087,
  "genres": [
    "Pretty Girl",
    "Hit On Girls",
    "Creampie",
    "Hd",
    "Big Breasts"
  ],
  "cast": [],
  "maker": "俺の素人",
  "sources": [
    {
      "name": "High Quality",
      "url": "https://hls.lustyflix.com/proxy?url=",
      "type": "hls"
    },
    {
      "name": "Medium Quality",
      "url": "https://hls.lustyflix.com/proxy?url=",
      "type": "hls"
    },
    {
      "name": "Low Quality",
      "url": "https://hls.lustyflix.com/proxy?url=",
      "type": "hls"
    }
  ],
  "url": "https://missav.ws/dm18/en/orec-582"
}