{
  "id": "pwife-675",
  "title": "PWIFE-675 Aya",
  "description": null,
  "poster": "https://fourhoi.com/pwife-675/cover-n.jpg",
  "release_date": "2020-09-08",
  "duration": 2698,
  "genres": [
    "Creampie",
    "Hd",
    "Slim Waist",
    "Big Breasts",
    "Brown Hair"
  ],
  "cast": [],
  "maker": "P-WIFE",
  "sources": [
    {
      "name": "High Quality",
      "url": "https://hls.lustyflix.com/proxy?url=",
      "type": "hls"
    },
    {
      "name": "Medium Quality",
      "url": "https://hls.lustyflix.com/proxy?url=",
      "type": "hls"
    },
    {
      "name": "Low Quality",
      "url": "https://hls.lustyflix.com/proxy?url=",
      "type": "hls"
    }
  ],
  "url": "https://missav.ws/en/pwife-675"
}