{
  "id": "ura-002",
  "title": "URA-002 Emil",
  "description": null,
  "poster": "https://fourhoi.com/ura-002/cover-n.jpg",
  "release_date": "2020-09-01",
  "duration": 3576,
  "genres": [
    "Planning",
    "Cosplay",
    "Creampie",
    "Selfie",
    "Hd",
    "Big Breasts"
  ],
  "cast": [],
  "maker": "黒船提督",
  "sources": [
    {
      "name": "High Quality",
      "url": "https://hls.lustyflix.com/proxy?url=",
      "type": "hls"
    },
    {
      "name": "Medium Quality",
      "url": "https://hls.lustyflix.com/proxy?url=",
      "type": "hls"
    },
    {
      "name": "Low Quality",
      "url": "https://hls.lustyflix.com/proxy?url=",
      "type": "hls"
    }
  ],
  "url": "https://missav.ws/dm18/en/ura-002"
}