{
  "id": "zmar-025",
  "title": "ZMAR-025 Marutto! Nozomi Tanihara",
  "description": "Nozomi Tanihara fascinates men who like mature women with her stunning E-cup boobs and bristle pussy that makes you want to suck on her beautiful face. Introducing all of her charms! \"Naked housewife\" who closely covers the naked private life of a full-time housewife. \"What if ...\" Nozomi Tanihara \"was XX ...\" ] 2 works are completely recorded!",
  "poster": "https://fourhoi.com/zmar-025/cover-n.jpg",
  "release_date": "2020-09-01",
  "duration": 14833,
  "genres": [
    "Mature Woman",
    "Big Breasts",
    "Slim",
    "Individual",
    "Creampie",
    "Hd",
    "Actress Collection"
  ],
  "cast": [
    "Nozomi Tanihara"
  ],
  "maker": "プラネットプラス",
  "sources": [
    {
      "name": "High Quality",
      "url": "https://hls.lustyflix.com/proxy?url=",
      "type": "hls"
    },
    {
      "name": "Medium Quality",
      "url": "https://hls.lustyflix.com/proxy?url=",
      "type": "hls"
    },
    {
      "name": "Low Quality",
      "url": "https://hls.lustyflix.com/proxy?url=",
      "type": "hls"
    }
  ],
  "url": "https://missav.ws/dm18/en/zmar-025"
}