{
  "id": "bank-014",
  "title": "BANK-014 Elder brother Mana Hirate who has sex with her sister while her parents are out - Mana Flat",
  "description": "Mana is famous for being cute even in the local area, and was annoying when invited by various men. I'm still young and have a quiet personality, so I couldn't refuse it clearly, and my brother often couldn't see it and dealt with it instead. I was reliant on such an older brother, and I always thought that a person like my brother would be nice to get married. One day, I saw my brother masturbating ... [* The image and sound may be disturbed, but please note that this is not a defect of the product itself.]",
  "poster": "https://fourhoi.com/bank-014/cover-n.jpg",
  "release_date": "2020-09-11",
  "duration": 6633,
  "genres": [
    "Uniform",
    "High School Girl",
    "Slim",
    "Incest",
    "Individual",
    "Elder Sister",
    "Creampie",
    "Hd"
  ],
  "cast": [
    "Mana Flat"
  ],
  "maker": "ま○こ銀行",
  "sources": [
    {
      "name": "High Quality",
      "url": "https://hls.lustyflix.com/proxy?url=",
      "type": "hls"
    },
    {
      "name": "Medium Quality",
      "url": "https://hls.lustyflix.com/proxy?url=",
      "type": "hls"
    },
    {
      "name": "Low Quality",
      "url": "https://hls.lustyflix.com/proxy?url=",
      "type": "hls"
    }
  ],
  "url": "https://missav.ws/dm18/en/bank-014"
}