{
  "id": "dvaj-427",
  "title": "DVAJ-427 My Big Stepsister Knows I'm Watching And Showing Off While She Fucks Nanami Kawakami - Kawakami Nanami",
  "description": "I want to get rid of it easily at a low price! The video that is perfect for you is [Tokodake]. Nasty wife sucks her brother-in-law's cock on the sleeping side of her husband! From the fellatio that sucks to the back, she begs for a cock and is fucked from behind. It is poked from the back to the front to the back, killing the voice and Iku. At the woman on top posture sleeping on the floor, each other swings their hips. While being poked by standing back again, my brother-in-law asked me to make a vaginal cum shot! * This work is a re-edited version of \"Nanami Kawakami, my sister-in-law who knows I'm peeking and shows off her squirrel\" (product number: dvaj00427).",
  "poster": "https://fourhoi.com/dvaj-427/cover-n.jpg",
  "release_date": "2020-08-28",
  "duration": 7766,
  "genres": [
    "Shame",
    "Wife",
    "Slim",
    "Incest",
    "Individual",
    "Creampie",
    "Hd",
    "Exclusive"
  ],
  "cast": [
    "Kawakami Nanami"
  ],
  "maker": "Alice Japan",
  "sources": [
    {
      "name": "High Quality",
      "url": "https://hls.lustyflix.com/proxy?url=",
      "type": "hls"
    },
    {
      "name": "Medium Quality",
      "url": "https://hls.lustyflix.com/proxy?url=",
      "type": "hls"
    },
    {
      "name": "Low Quality",
      "url": "https://hls.lustyflix.com/proxy?url=",
      "type": "hls"
    }
  ],
  "url": "https://missav.ws/dm18/en/dvaj-427"
}