{
  "id": "nash-355",
  "title": "NASH-355 Plump carnivorous mature woman big tits! Big butt! Comfortable to hold! A5 rank 10 people",
  "description": "Muchimuchi's Trofuwa body! Plump huge breasts! Just hugging a soft and ripe body makes you dreamy. !! Luxury marshmallow hug",
  "poster": "https://fourhoi.com/nash-355/cover-n.jpg",
  "release_date": "2020-08-28",
  "duration": 7164,
  "genres": [
    "Mature Woman",
    "Wife",
    "Creampie",
    "Collection",
    "Hd"
  ],
  "cast": [],
  "maker": "なでしこ",
  "sources": [
    {
      "name": "High Quality",
      "url": "https://hls.lustyflix.com/proxy?url=",
      "type": "hls"
    },
    {
      "name": "Medium Quality",
      "url": "https://hls.lustyflix.com/proxy?url=",
      "type": "hls"
    },
    {
      "name": "Low Quality",
      "url": "https://hls.lustyflix.com/proxy?url=",
      "type": "hls"
    }
  ],
  "url": "https://missav.ws/dm13/en/nash-355"
}