{
  "id": "jrzd-987",
  "title": "JRZD-987 First Shooting Married Woman Document Yukako Takamura",
  "description": "\"Even though I had sex with my husband in a rut, I haven't had much sex recently.\" Yukako Takamura, 47, has a wonderful sexual desire and dynamite body. A family of three, a full-time housewife who has been married for 20 years, a husband of an office worker, and a daughter of a school student. \"I used to ask for each other if I had free time ...\" Yukako who applied for this time because she wanted to have flirting sex with lots of affection like lovers. \"I want to be loved a lot today\" I will help her to resolve her dissatisfaction with the excitement of having sex after a long time, even though she is nervous at the first shooting. The amazingly constricted F cup round boobs have outstanding sensitivity and the feeling of rubbing is the best, a must-see! !!",
  "poster": "https://fourhoi.com/jrzd-987/cover-n.jpg",
  "release_date": "2020-08-27",
  "duration": 7978,
  "genres": [
    "Mature Woman",
    "Wife",
    "Documentary",
    "Individual",
    "Creampie",
    "Debut",
    "Hd"
  ],
  "cast": [
    "Yukako Takamura"
  ],
  "maker": "センタービレッジ",
  "sources": [
    {
      "name": "High Quality",
      "url": "https://hls.lustyflix.com/proxy?url=",
      "type": "hls"
    },
    {
      "name": "Medium Quality",
      "url": "https://hls.lustyflix.com/proxy?url=",
      "type": "hls"
    },
    {
      "name": "Low Quality",
      "url": "https://hls.lustyflix.com/proxy?url=",
      "type": "hls"
    }
  ],
  "url": "https://missav.ws/dm18/en/jrzd-987"
}