{
  "id": "docp-239",
  "title": "DOCP-239 \"Seriously angel !?\" My Ji ● Ko who can't masturbate because of a broken bone is the limit of patience! The beautiful nurse who couldn't see it was driven by a sense of mission, please kindly help me ... 8 - Uta Yumemite",
  "description": null,
  "poster": "https://fourhoi.com/docp-239/cover-n.jpg",
  "release_date": "2020-08-14",
  "duration": 14012,
  "genres": [
    "Uniform",
    "Nurse",
    "Creampie",
    "Hd"
  ],
  "cast": [
    "Uta Yumemite",
    "Mizuki Yayoi",
    "Yui Kawai",
    "Ran Tsukishiro"
  ],
  "maker": "Prestige",
  "sources": [
    {
      "name": "High Quality",
      "url": "https://hls.lustyflix.com/proxy?url=",
      "type": "hls"
    },
    {
      "name": "Medium Quality",
      "url": "https://hls.lustyflix.com/proxy?url=",
      "type": "hls"
    },
    {
      "name": "Low Quality",
      "url": "https://hls.lustyflix.com/proxy?url=",
      "type": "hls"
    }
  ],
  "url": "https://missav.ws/dm18/en/docp-239"
}