{
  "id": "bab-012",
  "title": "BAB-012 Too much fun of peeing bukkake fucking raw vaginal cum shot",
  "description": "It is a video that you can do as much as you want on a local date with a slender and compliant best beauty! (^^)! A video with plenty of sexual activity that exposes the true nature of a perverted woman from the ground up. Please enjoy it. Pee best grass",
  "poster": "https://fourhoi.com/bab-012/cover-n.jpg",
  "release_date": "2020-08-30",
  "duration": 4258,
  "genres": [
    "Hot Girl",
    "Slim",
    "Hit On Girls",
    "Outdoor Exposure",
    "Drink Urine",
    "Hd",
    "Exclusive",
    "Delusion"
  ],
  "cast": [],
  "maker": "バビロン/妄想族",
  "sources": [
    {
      "name": "High Quality",
      "url": "https://hls.lustyflix.com/proxy?url=",
      "type": "hls"
    },
    {
      "name": "Medium Quality",
      "url": "https://hls.lustyflix.com/proxy?url=",
      "type": "hls"
    },
    {
      "name": "Low Quality",
      "url": "https://hls.lustyflix.com/proxy?url=",
      "type": "hls"
    }
  ],
  "url": "https://missav.ws/dm19/en/bab-012"
}