{
  "id": "wnso-017",
  "title": "WNSO-017 Ema-chan",
  "description": null,
  "poster": "https://fourhoi.com/wnso-017/cover-n.jpg",
  "release_date": "2020-09-09",
  "duration": 4980,
  "genres": [
    "Ride",
    "Selfie",
    "Hd",
    "Beautiful Breasts",
    "Shaving",
    "White Skin"
  ],
  "cast": [],
  "maker": "ワンチャンすこすこ.com",
  "sources": [
    {
      "name": "High Quality",
      "url": "https://hls.lustyflix.com/proxy?url=",
      "type": "hls"
    },
    {
      "name": "Medium Quality",
      "url": "https://hls.lustyflix.com/proxy?url=",
      "type": "hls"
    },
    {
      "name": "Low Quality",
      "url": "https://hls.lustyflix.com/proxy?url=",
      "type": "hls"
    }
  ],
  "url": "https://missav.ws/dm18/en/wnso-017"
}