{
  "id": "dtt-063",
  "title": "DTT-063 The Most Erotic Married Woman In The History Of KANBi A Ripe And Voluptuous G-Cup Titty 39-Year Old Kasumi Ikeya Her Adult Video Debut This Horny Married Woman Who Frequently Participates In Many Orgy Parties Is Making Her Adult Video Debut!!",
  "description": null,
  "poster": "https://fourhoi.com/dtt-063/cover-n.jpg",
  "release_date": "2020-08-28",
  "duration": 7502,
  "genres": [
    "Mature Woman",
    "Wife",
    "Big Breasts",
    "Individual",
    "Forced Blowjob",
    "Debut",
    "Hd"
  ],
  "cast": [
    "Kasumi Ikeya"
  ],
  "maker": "Prestige",
  "sources": [
    {
      "name": "High Quality",
      "url": "https://hls.lustyflix.com/proxy?url=",
      "type": "hls"
    },
    {
      "name": "Medium Quality",
      "url": "https://hls.lustyflix.com/proxy?url=",
      "type": "hls"
    },
    {
      "name": "Low Quality",
      "url": "https://hls.lustyflix.com/proxy?url=",
      "type": "hls"
    }
  ],
  "url": "https://missav.ws/dm18/en/dtt-063"
}