{
  "id": "soud-001",
  "title": "SOUD-001 Midsummer super big boobs festival! Picking Up 20 Bikini Big Tits Beautiful Girls Over F Cup In The Pool At The Sea Immediately Man SP! !!",
  "description": null,
  "poster": "https://fourhoi.com/soud-001/cover-n.jpg",
  "release_date": "2020-09-04",
  "duration": 14575,
  "genres": [
    "Pretty Girl",
    "Big Breasts",
    "Swimsuit",
    "Collection",
    "Hd"
  ],
  "cast": [],
  "maker": "Prestige",
  "sources": [
    {
      "name": "High Quality",
      "url": "https://hls.lustyflix.com/proxy?url=",
      "type": "hls"
    },
    {
      "name": "Medium Quality",
      "url": "https://hls.lustyflix.com/proxy?url=",
      "type": "hls"
    },
    {
      "name": "Low Quality",
      "url": "https://hls.lustyflix.com/proxy?url=",
      "type": "hls"
    }
  ],
  "url": "https://missav.ws/dm18/en/soud-001"
}